autora/experimentalist/sampler/inequality/__init__.py
autora_experimentalist_sampler_inequality-1.0.1.dist-info/METADATA
autora_experimentalist_sampler_inequality-1.0.1.dist-info/WHEEL
autora_experimentalist_sampler_inequality-1.0.1.dist-info/top_level.txt
autora_experimentalist_sampler_inequality-1.0.1.dist-info/RECORD
