Metadata-Version: 2.1
Name: autora-experimentalist-sampler-inequality
Version: 1.0.1
Summary: AutoRA Inequality Sampler
Author-email: "Chad C. Williams" <cwilliams.uca@gmail.com>, Younes Strittmatter <younes_strittmatter@brown.com>
License: MIT License
Project-URL: homepage, http://www.empiricalresearch.ai
Project-URL: repository, https://github.com/AutoResearch/autora-experimentalist-sampler-inequality
Project-URL: documentation, https://autoresearch.github.io/autora/
Requires-Python: <4,>=3.8
Requires-Dist: autora-core
Provides-Extra: dev
Requires-Dist: autora-core[dev] ; extra == 'dev'
